<?xml version="1.0" encoding="UTF-8"?>
<metadata xml:lang="en"><Esri><CreaDate>20231204</CreaDate><CreaTime>09302500</CreaTime><ArcGISFormat>1.0</ArcGISFormat><SyncOnce>TRUE</SyncOnce><DataProperties><lineage><Process ToolSource="c:\program files\arcgis\pro\Resources\ArcToolbox\toolboxes\Data Management Tools.tbx\AddRelate" Date="20231204" Time="093025">AddRelate statistical-area-2-2018-generalised SA22018_V1 2018-census-main-means-of-travel-to-work-by-statistical-area SA2_code_u Relate1 "One to many"</Process><Process ToolSource="c:\program files\arcgis\pro\Resources\ArcToolbox\toolboxes\Data Management Tools.tbx\RemoveRelate" Date="20231204" Time="093614">RemoveRelate statistical-area-2-2018-generalised #</Process></lineage></DataProperties></Esri></metadata>
